seven_top/__init__.py
seven_top/top/__init__.py
seven_top/top/api/__init__.py
seven_top/top/api/base.py
seven_top/top/api/rest/AlibabaAliqinFcDigitalsmsCreatetemplateRequest.py
seven_top/top/api/rest/AlibabaAliqinTaNumberSinglecallbyttsRequest.py
seven_top/top/api/rest/AlibabaAliqinTaNumberSinglecallbyvoiceRequest.py
seven_top/top/api/rest/AlibabaAliqinTaSmsNumQueryRequest.py
seven_top/top/api/rest/AlibabaAliqinTaSmsNumSendRequest.py
seven_top/top/api/rest/AlibabaAliqinTaVoiceNumDoublecallRequest.py
seven_top/top/api/rest/AlibabaBenefitDrawRequest.py
seven_top/top/api/rest/AlibabaBenefitQueryRequest.py
seven_top/top/api/rest/AlibabaBenefitSendRequest.py
seven_top/top/api/rest/AlibabaBeneiftDrawRequest.py
seven_top/top/api/rest/AlibabaLafiteSellerActivityListRequest.py
seven_top/top/api/rest/AlibabaLafiteSellerBenefitListRequest.py
seven_top/top/api/rest/AlibabaLatourStrategyIssueRequest.py
seven_top/top/api/rest/AlibabaLatourStrategyShowRequest.py
seven_top/top/api/rest/AlibabaMemberPointChangeSyncRequest.py
seven_top/top/api/rest/AlibabaMemberSyncRequest.py
seven_top/top/api/rest/AlibabaShopCouponApplyRequest.py
seven_top/top/api/rest/AlipayXiaodaiUserPermitRequest.py
seven_top/top/api/rest/AppipGetRequest.py
seven_top/top/api/rest/AppstoreSubscribeGetRequest.py
seven_top/top/api/rest/ChattingPlatformNewuserUserGroupListRequest.py
seven_top/top/api/rest/ChattingPlatformNewuserUserJoinGroupInfoRequest.py
seven_top/top/api/rest/CrmGradeGetRequest.py
seven_top/top/api/rest/CrmGradeSetRequest.py
seven_top/top/api/rest/CrmGroupAddRequest.py
seven_top/top/api/rest/CrmGroupAppendRequest.py
seven_top/top/api/rest/CrmGroupDeleteRequest.py
seven_top/top/api/rest/CrmGroupMoveRequest.py
seven_top/top/api/rest/CrmGroupUpdateRequest.py
seven_top/top/api/rest/CrmGroupsGetRequest.py
seven_top/top/api/rest/CrmGrouptaskCheckRequest.py
seven_top/top/api/rest/CrmIndexEffectDataGetRequest.py
seven_top/top/api/rest/CrmIndexEffectivieDataGetRequest.py
seven_top-1.0.51.dist-info/LICENSE
seven_top-1.0.51.dist-info/METADATA
seven_top-1.0.51.dist-info/WHEEL
seven_top-1.0.51.dist-info/top_level.txt
seven_top-1.0.51.dist-info/RECORD
